src/mini_cpu.v
module mini_cpu (
    input wire clk,
    input wire reset,
    output reg done
);
    reg [7:0] pc;
    reg [7:0] acc;
    reg [7:0] instruction;

    reg [7:0] memory [0:255];

    reg [7:0] fetched_instruction;
    reg [1:0] opcode;
    reg [5:0] addr;

    localparam [1:0] OPC_LOAD = 2'b00;
    localparam [1:0] OPC_STORE = 2'b01;
    localparam [1:0] OPC_ADD = 2'b10;
    localparam [1:0] OPC_HALT = 2'b11;

    always @(posedge clk) begin
        if (reset) begin
            pc <= 8'd0;
            acc <= 8'd0;
            instruction <= 8'd0;
            done <= 1'b0;
        end else if (done) begin
            // Hold state once execution is complete.
            pc <= pc;
            acc <= acc;
            instruction <= instruction;
            done <= done;
        end else begin
            fetched_instruction = memory[pc];
            instruction <= fetched_instruction;
            opcode = fetched_instruction[7:6];
            addr = fetched_instruction[5:0];

            if (opcode == OPC_HALT) begin
                done <= 1'b1;
                pc <= pc;
            end else begin
                case (opcode)
                    OPC_LOAD: begin
                        acc <= memory[addr];
                    end
                    OPC_STORE: begin
                        memory[addr] <= acc;
                    end
                    OPC_ADD: begin
                        acc <= acc + memory[addr];
                    end
                    default: begin
                    end
                endcase

                pc <= pc + 8'd1;
                done <= 1'b0;
                end
        end
    end
endmodule

sim/tb_mini_cpu.v
`timescale 1ns/1ps

module tb_mini_cpu;
    reg clk;
    reg reset;
    wire done;

    string test_mode;
    string mem_file;
    integer expected_result;
    integer result_addr;
    integer program_len;

    integer cycle;
    integer i;

    reg [7:0] prev_mem_result;
    reg [7:0] curr_instr;
    reg [5:0] curr_addr;

    mini_cpu dut (
        .clk(clk),
        .reset(reset),
        .done(done)
    );

    // Decode instruction for readable cycle logs.
    function string instr_mnemonic;
        input [7:0] instr;
        begin
            if (instr[7:6] == 2'b11) begin
                instr_mnemonic = "HALT";
            end else begin
                case (instr[7:6])
                    2'b00: instr_mnemonic = "LOAD";
                    2'b01: instr_mnemonic = "STORE";
                    2'b10: instr_mnemonic = "ADD";
                    default: instr_mnemonic = "UNK";
                endcase
            end
        end
    endfunction

    task print_header;
        begin
            $display("==============================================================================================");
            $display(" Cycle |  PC  | Instruction           |   ACC(dec/hex)   | Memory Activity");
            $display("----------------------------------------------------------------------------------------------");
        end
    endtask

    task print_cycle_row;
        input integer cyc;
        input [7:0] pc_value;
        input [7:0] instr;
        input [7:0] acc_value;
        begin
            if (instr[7:6] == 2'b01) begin
                $display(
                    " %5d | %4d | %-5s %2d (0x%02h) | %6d / 0x%02h    | STORE -> M[%0d] = %0d (0x%02h)",
                    cyc,
                    pc_value,
                    instr_mnemonic(instr),
                    instr[5:0],
                    instr,
                    acc_value,
                    acc_value,
                    instr[5:0],
                    dut.memory[instr[5:0]],
                    dut.memory[instr[5:0]]
                );
            end else if (instr[7:6] == 2'b11) begin
                $display(
                    " %5d | %4d | HALT      (0x%02h)    | %6d / 0x%02h    | done asserted",
                    cyc,
                    pc_value,
                    instr,
                    acc_value,
                    acc_value
                );
            end else begin
                $display(
                    " %5d | %4d | %-5s %2d (0x%02h) | %6d / 0x%02h    | -",
                    cyc,
                    pc_value,
                    instr_mnemonic(instr),
                    instr[5:0],
                    instr,
                    acc_value,
                    acc_value
                );
            end
        end
    endtask

    initial begin
        clk = 1'b0;
        forever #50 clk = ~clk; // 100 ns period
    end

    initial begin
        $dumpfile("sim/mini_cpu.vcd");
        $dumpvars(0, tb_mini_cpu);
    end

    initial begin
        reset = 1'b1;
        cycle = 0;

        if (!$value$plusargs("TEST=%s", test_mode)) begin
            test_mode = "add";
        end

        if (test_mode == "sum") begin
            mem_file = "mem/sum_1_to_5.mem";
            expected_result = 15;
            result_addr = 30;
            program_len = 7;
        end else if (test_mode == "calc") begin
            mem_file = "mem/calculator.mem";
            expected_result = 25;
            result_addr = 42;
            program_len = 4;
        end else begin
            test_mode = "add";
            mem_file = "mem/add_two_numbers.mem";
            expected_result = 12;
            result_addr = 12;
            program_len = 4;
        end

        for (i = 0; i < 256; i = i + 1) begin
            dut.memory[i] = 8'h00;
        end

        $readmemh(mem_file, dut.memory, 0, program_len - 1);

        if (test_mode == "sum") begin
            dut.memory[8'd20] = 8'd1;
            dut.memory[8'd21] = 8'd2;
            dut.memory[8'd22] = 8'd3;
            dut.memory[8'd23] = 8'd4;
            dut.memory[8'd24] = 8'd5;
            dut.memory[8'd30] = 8'd0;
        end else if (test_mode == "calc") begin
            dut.memory[8'd40] = 8'd9;
            dut.memory[8'd41] = 8'd16;
            dut.memory[8'd42] = 8'd0;
        end else begin
            dut.memory[8'd10] = 8'd7;
            dut.memory[8'd11] = 8'd5;
            dut.memory[8'd12] = 8'd0;
        end

        prev_mem_result = dut.memory[result_addr];

        $display("\nStarting TEST=%0s, program=%0s, expected M[%0d]=%0d", test_mode, mem_file, result_addr, expected_result);
        print_header();

        repeat (2) @(posedge clk);
        reset = 1'b0;
        @(posedge clk);

        while (!done && (cycle < 200)) begin
            @(negedge clk);
            curr_instr = dut.instruction;
            curr_addr = curr_instr[5:0];
            print_cycle_row(cycle, dut.pc, curr_instr, dut.acc);

            if ((curr_instr[7:6] == 2'b01) && (dut.memory[curr_addr] != prev_mem_result)) begin
                $display("         *** memory change detected: M[%0d] now %0d (0x%02h)", curr_addr, dut.memory[curr_addr], dut.memory[curr_addr]);
            end

            prev_mem_result = dut.memory[result_addr];
            cycle = cycle + 1;
        end

        if (!done) begin
            $fatal(1, "Timeout waiting for done. TEST=%0s", test_mode);
        end

        $display("----------------------------------------------------------------------------------------------");
        $display("Done at cycle %0d. Final: PC=%0d ACC=%0d (0x%02h) M[%0d]=%0d", cycle, dut.pc, dut.acc, dut.acc, result_addr, dut.memory[result_addr]);

        if (dut.memory[result_addr] !== expected_result[7:0]) begin
            $fatal(1, "ASSERT FAIL (%0s): M[%0d]=%0d expected %0d", test_mode, result_addr, dut.memory[result_addr], expected_result);
        end else begin
            $display("ASSERT PASS (%0s): M[%0d]=%0d", test_mode, result_addr, dut.memory[result_addr]);
        end

        $finish;
    end
endmodule

sim/waves/sum.vcd
$date
	Tue Mar 31 22:46:56 2026
$end
$version
	Icarus Verilog
$end
$timescale
	1ps
$end
$scope module tb_mini_cpu $end
$var wire 1 ! done $end
$var reg 1 " clk $end
$var reg 6 # curr_addr [5:0] $end
$var reg 8 $ curr_instr [7:0] $end
$var reg 8 % prev_mem_result [7:0] $end
$var reg 1 & reset $end
$var integer 32 ' cycle [31:0] $end
$var integer 32 ( expected_result [31:0] $end
$var integer 32 ) i [31:0] $end
$var integer 32 * program_len [31:0] $end
$var integer 32 + result_addr [31:0] $end
$scope function instr_mnemonic $end
$var reg 8 , instr [7:0] $end
$upscope $end
$scope module dut $end
$var wire 1 " clk $end
$var wire 1 & reset $end
$var parameter 2 - OPC_ADD $end
$var parameter 2 . OPC_HALT $end
$var parameter 2 / OPC_LOAD $end
$var parameter 2 0 OPC_STORE $end
$var reg 8 1 acc [7:0] $end
$var reg 6 2 addr [5:0] $end
$var reg 1 ! done $end
$var reg 8 3 fetched_instruction [7:0] $end
$var reg 8 4 instruction [7:0] $end
$var reg 2 5 opcode [1:0] $end
$var reg 8 6 pc [7:0] $end
$upscope $end
$scope task print_cycle_row $end
$var reg 8 7 acc_value [7:0] $end
$var reg 8 8 instr [7:0] $end
$var reg 8 9 pc_value [7:0] $end
$var integer 32 : cyc [31:0] $end
$upscope $end
$scope task print_header $end
$upscope $end
$upscope $end
$enddefinitions $end
$comment Show the parameter values. $end
$dumpall
b1 0
b0 /
b11 .
b10 -
$end
#0
$dumpvars
bx :
bx 9
bx 8
bx 7
bx 6
bx 5
bx 4
bx 3
bx 2
bx 1
bx ,
b11110 +
b111 *
b100000000 )
b1111 (
b0 '
1&
b0 %
bx $
bx #
0"
x!
$end
#50000
0!
b0 4
b0 1
b0 6
1"
#100000
0"
#150000
0&
1"
#200000
0"
#250000
b1 6
b1 1
b10100 4
b10100 2
b0 5
b10100 3
1"
#300000
b1 '
b10100 ,
b1 7
b10100 8
b1 9
b0 :
b10100 #
b10100 $
0"
#350000
b10 6
b11 1
b10010101 4
b10101 2
b10 5
b10010101 3
1"
#400000
b10 '
b10010101 ,
b11 7
b10010101 8
b10 9
b1 :
b10101 #
b10010101 $
0"
#450000
b11 6
b110 1
b10010110 4
b10110 2
b10010110 3
1"
#500000
b11 '
b10010110 ,
b110 7
b10010110 8
b11 9
b10 :
b10110 #
b10010110 $
0"
#550000
b100 6
b1010 1
b10010111 4
b10111 2
b10010111 3
1"
#600000
b100 '
b10010111 ,
b1010 7
b10010111 8
b100 9
b11 :
b10111 #
b10010111 $
0"
#650000
b101 6
b1111 1
b10011000 4
b11000 2
b10011000 3
1"
#700000
b101 '
b10011000 ,
b1111 7
b10011000 8
b101 9
b100 :
b11000 #
b10011000 $
0"
#750000
b110 6
b1011110 4
b11110 2
b1 5
b1011110 3
1"
#800000
b110 '
b1111 %
b1011110 ,
b1011110 8
b110 9
b101 :
b11110 #
b1011110 $
0"
#850000
1!
b11000000 4
b0 2
b11 5
b11000000 3
1"
#900000
b111 '
b11000000 8
b110 :
b0 #
b11000000 $
0"
